{
    "cad": {
        "aed": 2.887051,
        "afn": 60.681567,
        "all": 79.900017,
        "amd": 408.193584,
        "ang": 1.41126,
        "aoa": 515.934807,
        "ars": 67.760245,
        "aud": 1.019032,
        "awg": 1.414855,
        "azn": 1.336252,
        "bam": 1.267943,
        "bbd": 1.5874,
        "bch": 0.001519,
        "bdt": 66.665737,
        "bgn": 1.267628,
        "bhd": 0.296388,
        "bif": 1536.689946,
        "bmd": 0.786031,
        "bnd": 1.044523,
        "bob": 5.412951,
        "brl": 4.211631,
        "bsd": 0.78618,
        "btc": 0.000022,
        "btn": 57.512677,
        "bwp": 8.601754,
        "byr": 2.002953,
        "bzd": 1.584742,
        "cad": 1,
        "cdf": 1548.480406,
        "chf": 0.697744,
        "clf": 0.019924,
        "clp": 579.540408,
        "cnh": 5.089666,
        "cny": 5.092693,
        "cop": 2744.551825,
        "crc": 478.884387,
        "cup": 18.868768,
        "cve": 71.7646,
        "czk": 16.935817,
        "djf": 139.693369,
        "dkk": 4.814454,
        "dop": 45.707683,
        "dzd": 104.544593,
        "egp": 12.349092,
        "etb": 30.930307,
        "eth": 0.000562,
        "eur": 0.647182,
        "fjd": 1.607786,
        "gbp": 0.575925,
        "gel": 2.593901,
        "ghs": 4.61007,
        "gmd": 40.673157,
        "gnf": 7997.861997,
        "gqe": 425.249506,
        "gtq": 6.124514,
        "gyd": 164.483833,
        "hkd": 6.093506,
        "hnl": 19.084824,
        "hrk": 4.896578,
        "htg": 57.140821,
        "huf": 231.666031,
        "idr": 11072.263729,
        "ils": 2.553366,
        "inr": 57.531353,
        "iqd": 1149.569845,
        "irr": 33095.821068,
        "isk": 101.618044,
        "jmd": 113.385709,
        "jod": 0.557296,
        "jpy": 81.619852,
        "kes": 86.620579,
        "kgs": 66.655007,
        "khr": 3187.354339,
        "kmf": 319.089148,
        "kpw": 2.840479,
        "krw": 864.716263,
        "kwd": 0.238262,
        "kyd": 0.655225,
        "kzt": 330.154023,
        "lak": 7329.735933,
        "lbp": 1193.194547,
        "lkr": 152.133327,
        "lrd": 132.839182,
        "lsl": 11.971247,
        "ltc": 0.005071,
        "lyd": 3.513557,
        "mad": 7.016896,
        "mdl": 13.624828,
        "mga": 2955.475293,
        "mkd": 39.932126,
        "mmk": 1047.217648,
        "mnt": 2220.536623,
        "mop": 6.277444,
        "mru": 28.568284,
        "mur": 31.126814,
        "mvr": 12.128453,
        "mwk": 605.243611,
        "mxn": 15.440283,
        "myr": 3.180673,
        "mzm": 59.015182,
        "mzn": 58.362777,
        "nad": 11.939806,
        "ngn": 299.634889,
        "nio": 27.511073,
        "nok": 6.69989,
        "npr": 92.02006,
        "nzd": 1.102318,
        "omr": 0.302577,
        "pab": 0.786244,
        "pen": 2.841108,
        "pgk": 2.774688,
        "php": 37.792354,
        "pkr": 126.197223,
        "pln": 2.936335,
        "pyg": 5401.153107,
        "qar": 2.861741,
        "ron": 3.154734,
        "rsd": 76.559387,
        "rub": 57.9946,
        "rwf": 779.349402,
        "sar": 2.947862,
        "sbd": 6.264784,
        "scr": 16.667796,
        "sdg": 43.487146,
        "sek": 6.549479,
        "sgd": 1.043676,
        "shp": 0.576868,
        "sll": 8009.652457,
        "sos": 459.434923,
        "srd": 11.125478,
        "svc": 6.879641,
        "syp": 987.254513,
        "szl": 11.963387,
        "thb": 23.551051,
        "tjs": 8.958769,
        "tmt": 2.758968,
        "tnd": 2.125427,
        "top": 1.802054,
        "try": 5.871335,
        "ttd": 5.329452,
        "twd": 21.993138,
        "tzs": 1823.195765,
        "uah": 22.111381,
        "ugx": 2901.09219,
        "usd": 0.786031,
        "uyu": 9.068223,
        "uzs": 2248.125323,
        "vef": 1174092.429346,
        "vnd": 4937.208499,
        "vuv": 83.515758,
        "xaf": 420.227713,
        "xcd": 2.124287,
        "xof": 115.990854,
        "xpf": 77.758083,
        "yer": 53.576218,
        "zar": 11.785429,
        "zmw": 4.565706
    }
}