{
    "date": "2022-02-13",
    "sek": {
        "ada": 0.100148,
        "aed": 0.393152,
        "afn": 9.893125,
        "all": 11.453014,
        "amd": 51.582887,
        "ang": 0.193675,
        "aoa": 56.487728,
        "ars": 11.392844,
        "aud": 0.149993,
        "awg": 0.19269,
        "azn": 0.182385,
        "bam": 0.184454,
        "bbd": 0.216979,
        "bch": 0.000322,
        "bdt": 9.239255,
        "bgn": 0.183755,
        "bhd": 0.040355,
        "bif": 214.725145,
        "bmd": 0.107035,
        "bnb": 0.000264,
        "bnd": 0.144455,
        "bob": 0.739891,
        "brl": 0.562361,
        "bsd": 0.107466,
        "btc": 0.000003,
        "btn": 8.087286,
        "bwp": 1.237357,
        "byn": 0.274735,
        "byr": 2097.892205,
        "bzd": 0.216621,
        "cad": 0.136319,
        "cdf": 215.676202,
        "chf": 0.09913,
        "clf": 0.003126,
        "clp": 86.267072,
        "cny": 0.680167,
        "cop": 421.688572,
        "crc": 69.07929,
        "cuc": 0.107035,
        "cup": 2.836436,
        "cve": 10.399099,
        "czk": 2.316598,
        "djf": 19.131739,
        "dkk": 0.701692,
        "doge": 0.737427,
        "dop": 6.144772,
        "dzd": 15.073895,
        "egp": 1.681737,
        "ern": 1.605532,
        "etb": 5.407899,
        "etc": 0.003305,
        "eth": 0.000036,
        "eur": 0.094309,
        "fjd": 0.228467,
        "fkp": 0.077913,
        "gbp": 0.07892,
        "gel": 0.313655,
        "ggp": 0.077913,
        "ghs": 0.68885,
        "gip": 0.077913,
        "gmd": 5.683988,
        "gnf": 969.007575,
        "gtq": 0.826401,
        "gyd": 22.483518,
        "hkd": 0.834927,
        "hnl": 2.645869,
        "hrk": 0.710291,
        "htg": 10.986839,
        "huf": 33.616623,
        "idr": 1535.394857,
        "ils": 0.346328,
        "imp": 0.077913,
        "inr": 8.064951,
        "iqd": 156.844232,
        "irr": 4522.242162,
        "isk": 13.381597,
        "jep": 0.077913,
        "jmd": 16.891215,
        "jod": 0.075892,
        "jpy": 12.405076,
        "kes": 12.207956,
        "kgs": 9.074947,
        "khr": 437.268594,
        "kmf": 46.24465,
        "kpw": 96.331802,
        "krw": 128.420442,
        "kwd": 0.032351,
        "kyd": 0.089557,
        "kzt": 46.214759,
        "lak": 1220.796574,
        "lbp": 162.505665,
        "link": 0.006676,
        "lkr": 21.761546,
        "lrd": 16.441029,
        "lsl": 1.629118,
        "ltc": 0.000841,
        "ltl": 0.316047,
        "lvl": 0.064745,
        "lyd": 0.492449,
        "mad": 1.003535,
        "mdl": 1.912863,
        "mga": 427.977167,
        "mkd": 5.812329,
        "mmk": 191.077143,
        "mnt": 305.995899,
        "mop": 0.863399,
        "mro": 38.21159,
        "mur": 4.683438,
        "mvr": 1.653736,
        "mwk": 86.127342,
        "mxn": 2.199025,
        "myr": 0.448425,
        "mzn": 6.832105,
        "nad": 1.629118,
        "ngn": 44.634838,
        "nio": 3.810126,
        "nok": 0.951908,
        "npr": 12.939623,
        "nzd": 0.160968,
        "omr": 0.041211,
        "pab": 0.107466,
        "pen": 0.401846,
        "pgk": 0.380607,
        "php": 5.487431,
        "pkr": 18.768664,
        "pln": 0.43124,
        "pyg": 749.095377,
        "qar": 0.38972,
        "ron": 0.46645,
        "rsd": 11.086758,
        "rub": 8.219606,
        "rwf": 111.711209,
        "sar": 0.401576,
        "sbd": 0.865635,
        "scr": 1.400693,
        "sdg": 47.363521,
        "sek": 1,
        "sgd": 0.144253,
        "shp": 0.147431,
        "sll": 1232.511706,
        "sos": 62.508661,
        "srd": 2.179778,
        "std": 2215.414949,
        "svc": 0.940366,
        "syp": 268.872691,
        "szl": 1.626613,
        "thb": 3.501557,
        "theta": 0.027428,
        "tjs": 1.213808,
        "tmt": 0.374624,
        "tnd": 0.308694,
        "top": 0.242751,
        "trx": 1.679118,
        "try": 1.447129,
        "ttd": 0.730365,
        "twd": 2.987253,
        "tzs": 248.565481,
        "uah": 3.011311,
        "ugx": 378.485133,
        "usd": 0.107035,
        "usdt": 0.106212,
        "uyu": 4.647883,
        "uzs": 1166.122202,
        "vef": 22887385538.42297,
        "vnd": 2428.363744,
        "vuv": 12.166856,
        "wst": 0.279613,
        "xaf": 61.863344,
        "xag": 0.004753,
        "xau": 0.000059,
        "xcd": 0.289268,
        "xdr": 0.076551,
        "xlm": 0.487384,
        "xmr": 0.000618,
        "xof": 61.863344,
        "xpf": 11.286913,
        "xrp": 0.128134,
        "yer": 26.785627,
        "zar": 1.628723,
        "zmk": 963.446676,
        "zmw": 2.016028,
        "zwl": 34.465328
    }
}