{
    "date": "2022-06-05",
    "top": {
        "1inch": 0.505016,
        "aave": 0.004118,
        "ada": 0.774274,
        "aed": 1.597555,
        "afn": 38.77992,
        "algo": 1.128416,
        "all": 48.809629,
        "amd": 194.532543,
        "amp": 37.715521,
        "ang": 0.785377,
        "aoa": 185.357987,
        "ar": 0.034198,
        "ars": 52.484836,
        "atom": 0.047524,
        "aud": 0.603487,
        "avax": 0.017881,
        "awg": 0.783097,
        "axs": 0.021495,
        "azn": 0.741113,
        "bam": 0.793544,
        "bat": 1.150786,
        "bbd": 0.879872,
        "bch": 0.002317,
        "bdt": 38.799963,
        "bgn": 0.792193,
        "bhd": 0.164281,
        "bif": 896.080691,
        "bmd": 0.434933,
        "bnb": 0.001458,
        "bnd": 0.598699,
        "bob": 3.000352,
        "brl": 2.076824,
        "bsd": 0.435797,
        "bsv": 0.007647,
        "btc": 0.000015,
        "btcb": 0.000015,
        "btg": 0.020059,
        "btn": 33.82418,
        "busd": 0.433933,
        "bwp": 5.218979,
        "byn": 1.47147,
        "byr": 8524.689826,
        "bzd": 0.878411,
        "cad": 0.54769,
        "cake": 0.1027,
        "cdf": 871.39028,
        "celo": 0.341256,
        "chf": 0.4183,
        "chz": 3.395497,
        "clf": 0.012796,
        "clp": 353.083256,
        "cny": 2.896787,
        "comp": 0.00754,
        "cop": 1644.637015,
        "crc": 297.548045,
        "cro": 2.432149,
        "crv": 0.372484,
        "cuc": 0.434933,
        "cup": 11.525728,
        "cve": 44.738103,
        "cvx": 0.051574,
        "czk": 10.007422,
        "dai": 0.434772,
        "dash": 0.007436,
        "dcr": 0.012475,
        "dfi": 12.322924,
        "djf": 77.580127,
        "dkk": 3.018014,
        "doge": 5.336144,
        "dop": 24.01166,
        "dot": 0.04624,
        "dzd": 63.243801,
        "egld": 0.005653,
        "egp": 8.102885,
        "enj": 0.704104,
        "eos": 0.339971,
        "ern": 6.523998,
        "etb": 22.648885,
        "etc": 0.019899,
        "eth": 0.000242,
        "eur": 0.405728,
        "fei": 0.437541,
        "fil": 0.05831,
        "fjd": 0.929367,
        "fkp": 0.355919,
        "flow": 0.176298,
        "frax": 0.435233,
        "ftm": 1.240885,
        "ftt": 0.016777,
        "gala": 5.905606,
        "gbp": 0.348267,
        "gel": 1.289594,
        "ggp": 0.355919,
        "ghs": 3.41002,
        "gip": 0.355919,
        "gmd": 23.5518,
        "gnf": 3858.192255,
        "gno": 0.002306,
        "grt": 2.621467,
        "gt": 0.080871,
        "gtq": 3.353339,
        "gyd": 91.172168,
        "hbar": 4.702738,
        "hkd": 3.411965,
        "hnl": 10.709312,
        "hnt": 0.045376,
        "hot": 202.989054,
        "hrk": 3.05071,
        "ht": 0.061256,
        "htg": 49.67952,
        "huf": 159.024778,
        "icp": 0.056743,
        "idr": 6277.607684,
        "ils": 1.450519,
        "imp": 0.355919,
        "inj": 0.213484,
        "inr": 33.757121,
        "iqd": 636.026393,
        "irr": 18397.672584,
        "isk": 56.119593,
        "jep": 0.355919,
        "jmd": 67.058264,
        "jod": 0.308891,
        "jpy": 56.908846,
        "kava": 0.173197,
        "kcs": 0.026083,
        "kda": 0.21953,
        "kes": 50.877689,
        "kgs": 34.578839,
        "khr": 1769.72437,
        "klay": 1.082197,
        "kmf": 199.525752,
        "knc": 0.221498,
        "kpw": 391.439936,
        "krw": 544.332058,
        "ksm": 0.006322,
        "kwd": 0.133207,
        "kyd": 0.363131,
        "kzt": 189.456829,
        "lak": 6081.363357,
        "lbp": 658.909711,
        "leo": 0.087494,
        "link": 0.058755,
        "lkr": 157.099858,
        "lrc": 0.848598,
        "lrd": 66.109991,
        "lsl": 6.73728,
        "ltc": 0.006866,
        "ltl": 1.284245,
        "luna": 0.068611,
        "lvl": 0.263087,
        "lyd": 2.081611,
        "mad": 4.296586,
        "mana": 0.447352,
        "matic": 0.731556,
        "mdl": 8.292971,
        "mga": 1763.833133,
        "mina": 0.514144,
        "miota": 1.246141,
        "mkd": 25.005299,
        "mkr": 0.000373,
        "mmk": 806.85255,
        "mnt": 1337.754695,
        "mop": 3.520866,
        "mro": 155.271061,
        "mur": 18.76753,
        "mvr": 6.71321,
        "mwk": 445.357236,
        "mxn": 8.500834,
        "myr": 1.909808,
        "mzn": 27.761947,
        "nad": 6.737279,
        "near": 0.082078,
        "neo": 0.038665,
        "nexo": 0.361936,
        "ngn": 180.549615,
        "nio": 15.622733,
        "nok": 4.104225,
        "npr": 54.11864,
        "nzd": 0.667946,
        "okb": 0.038027,
        "omr": 0.167458,
        "one": 565.576687,
        "pab": 0.435757,
        "paxg": 0.000234,
        "pen": 1.6151,
        "pgk": 1.535536,
        "php": 23.012476,
        "pkr": 86.176139,
        "pln": 1.862493,
        "pyg": 2984.203703,
        "qar": 1.583608,
        "qnt": 0.00668,
        "qtum": 0.112917,
        "ron": 2.005494,
        "rsd": 47.64112,
        "rub": 27.557527,
        "rune": 0.154808,
        "rwf": 444.69508,
        "sand": 0.338204,
        "sar": 1.631289,
        "sbd": 3.530339,
        "scr": 5.615258,
        "sdg": 198.113652,
        "sek": 4.148103,
        "sgd": 0.597585,
        "shib": 40114.270774,
        "shp": 0.599079,
        "sll": 5669.353815,
        "sol": 0.011299,
        "sos": 253.566176,
        "srd": 9.287144,
        "std": 9002.238169,
        "stx": 101.608589,
        "svc": 3.813075,
        "syp": 1092.748029,
        "szl": 6.746805,
        "thb": 14.915179,
        "theta": 0.365491,
        "tjs": 4.88076,
        "tmt": 1.526615,
        "tnd": 1.313659,
        "top": 1,
        "trx": 5.441641,
        "try": 7.14056,
        "ttd": 2.953896,
        "ttt": 0.133696,
        "tusd": 0.434849,
        "twd": 12.776178,
        "tzs": 1014.067725,
        "uah": 12.812021,
        "ugx": 1629.178604,
        "uni": 2923.196504,
        "usd": 0.434933,
        "usdc": 0.43491,
        "usdp": 0.43526,
        "usdt": 0.435242,
        "uyu": 17.452993,
        "uzs": 4791.291987,
        "vef": 93001853107.33104,
        "vet": 14.333253,
        "vnd": 10086.969717,
        "vuv": 49.697925,
        "waves": 0.051275,
        "wbtc": 0.000015,
        "wemix": 0.11509,
        "wst": 1.121842,
        "xaf": 266.143126,
        "xag": 0.019839,
        "xau": 0.000235,
        "xcd": 1.175429,
        "xdc": 11.356058,
        "xdr": 0.323247,
        "xec": 9026.73902,
        "xem": 8.523419,
        "xlm": 3.057888,
        "xmr": 0.0023,
        "xof": 266.143126,
        "xpf": 48.496612,
        "xrp": 1.107306,
        "xtz": 0.229363,
        "yer": 108.84218,
        "zar": 6.760394,
        "zec": 0.00484,
        "zil": 8.683384,
        "zmk": 3914.921872,
        "zmw": 7.408312,
        "zwl": 140.048298
    }
}