{
    "sar": {
        "aed": 0.979396,
        "afn": 20.921406,
        "all": 27.628054,
        "amd": 122.101873,
        "ang": 0.478829,
        "aoa": 167.529491,
        "ars": 24.599371,
        "aud": 0.350422,
        "awg": 0.479939,
        "azn": 0.453276,
        "bam": 0.438709,
        "bbd": 0.538609,
        "bch": 0.000433,
        "bdt": 22.619613,
        "bgn": 0.43927,
        "bhd": 0.100522,
        "bif": 519.470872,
        "bmd": 0.266633,
        "bnd": 0.357169,
        "bob": 1.841922,
        "brl": 1.496771,
        "bsd": 0.266747,
        "btc": 0.000005,
        "btn": 19.7678,
        "bwp": 2.915357,
        "byr": 0.710967,
        "bzd": 0.537689,
        "cad": 0.336404,
        "cdf": 532.732663,
        "chf": 0.247874,
        "clf": 0.006471,
        "clp": 190.295947,
        "cnh": 1.74703,
        "cny": 1.744446,
        "cop": 974.434165,
        "crc": 163.5036,
        "cup": 6.402255,
        "cve": 24.733348,
        "czk": 5.809959,
        "djf": 47.38601,
        "dkk": 1.670549,
        "dop": 15.172818,
        "dzd": 35.363397,
        "egp": 4.186884,
        "etb": 11.060125,
        "eth": 0.000136,
        "eur": 0.224532,
        "fjd": 0.551024,
        "gbp": 0.194061,
        "gel": 0.913218,
        "ghs": 1.54185,
        "gmd": 13.664939,
        "gnf": 2668.865322,
        "gqe": 147.137802,
        "gtq": 2.05873,
        "gyd": 55.758312,
        "hkd": 2.075724,
        "hnl": 6.415154,
        "hrk": 1.701465,
        "htg": 21.593615,
        "huf": 80.665004,
        "idr": 3905.839635,
        "ils": 0.878009,
        "inr": 19.837959,
        "iqd": 389.198272,
        "irr": 11226.58096,
        "isk": 33.825058,
        "jmd": 38.965981,
        "jod": 0.189043,
        "jpy": 29.301896,
        "kes": 28.863018,
        "kgs": 22.606982,
        "khr": 1079.021478,
        "kmf": 111.665885,
        "kpw": 0.962012,
        "krw": 298.840893,
        "kwd": 0.080504,
        "kyd": 0.222311,
        "kzt": 115.61296,
        "lak": 2513.350046,
        "lbp": 403.326886,
        "lkr": 53.4313,
        "lrd": 46.127503,
        "lsl": 3.908839,
        "ltc": 0.001219,
        "lyd": 1.209492,
        "mad": 2.398304,
        "mdl": 4.793578,
        "mga": 1016.329403,
        "mkd": 13.840429,
        "mmk": 376.126591,
        "mnt": 755.371188,
        "mop": 2.138842,
        "mru": 9.606786,
        "mur": 10.692225,
        "mvr": 4.122146,
        "mwk": 209.474056,
        "mxn": 5.390868,
        "myr": 1.101594,
        "mzm": 17.472458,
        "mzn": 17.288481,
        "nad": 3.908839,
        "ngn": 101.600491,
        "nio": 9.309767,
        "nok": 2.259692,
        "npr": 31.628402,
        "nzd": 0.380361,
        "omr": 0.102656,
        "pab": 0.266782,
        "pen": 0.969254,
        "pgk": 0.936831,
        "php": 13.033153,
        "pkr": 40.833719,
        "pln": 1.027163,
        "pyg": 1700.944734,
        "qar": 0.970744,
        "ron": 1.10458,
        "rsd": 26.37977,
        "rub": 20.542737,
        "rwf": 265.329742,
        "sar": 1,
        "sbd": 2.12969,
        "scr": 5.099542,
        "sdg": 101.453843,
        "sek": 2.297974,
        "sgd": 0.357557,
        "shp": 0.193122,
        "sll": 2722.989148,
        "sos": 156.246917,
        "srd": 3.773923,
        "svc": 2.334152,
        "syp": 334.891003,
        "szl": 3.878872,
        "thb": 8.366942,
        "tjs": 3.04153,
        "tmt": 0.935882,
        "tnd": 0.745372,
        "top": 0.60855,
        "try": 2.176632,
        "ttd": 1.812119,
        "twd": 7.565284,
        "tzs": 618.321844,
        "uah": 7.454482,
        "ugx": 973.116465,
        "usd": 0.266633,
        "uyu": 3.210235,
        "uzs": 761.0204,
        "vef": 529252.035876,
        "vnd": 1676.255589,
        "vuv": 28.660377,
        "xaf": 145.824234,
        "xcd": 0.720589,
        "xof": 40.056778,
        "xpf": 27.163233,
        "yer": 18.172592,
        "zar": 3.886882,
        "zmw": 1.606395
    }
}