{
    "date": "2021-10-29",
    "shp": {
        "ada": 0.363868,
        "aed": 2.666765,
        "afn": 65.88497,
        "all": 76.412029,
        "amd": 346.87823,
        "ang": 1.308325,
        "aoa": 433.425464,
        "ars": 72.345143,
        "aud": 0.963767,
        "awg": 1.30681,
        "azn": 1.234897,
        "bam": 1.223293,
        "bbd": 1.465765,
        "bch": 0.001254,
        "bdt": 62.194904,
        "bgn": 1.215772,
        "bhd": 0.273707,
        "bif": 1448.38103,
        "bmd": 0.726005,
        "bnb": 0.001479,
        "bnd": 0.977852,
        "bob": 5.012579,
        "brl": 4.099536,
        "bsd": 0.725971,
        "btc": 0.000012,
        "btn": 54.34601,
        "bwp": 8.221356,
        "byn": 1.762483,
        "byr": 14229.708365,
        "bzd": 1.463263,
        "cad": 0.89629,
        "cdf": 1462.17491,
        "chf": 0.661819,
        "clf": 0.021204,
        "clp": 585.080746,
        "cny": 4.640554,
        "cop": 2743.937896,
        "crc": 459.881788,
        "cuc": 0.726005,
        "cup": 19.239146,
        "cve": 68.75095,
        "czk": 15.998041,
        "djf": 129.02599,
        "dkk": 4.621693,
        "doge": 2.41918,
        "dop": 40.983088,
        "dzd": 99.070465,
        "egp": 11.404354,
        "ern": 10.890982,
        "etb": 34.231104,
        "etc": 0.013931,
        "eth": 0.00017,
        "eur": 0.62129,
        "fjd": 1.498511,
        "fkp": 0.532323,
        "gbp": 0.5261,
        "gel": 2.286942,
        "ggp": 0.532323,
        "ghs": 4.42163,
        "gip": 0.532323,
        "gmd": 37.752246,
        "gnf": 6995.063177,
        "gtq": 5.618707,
        "gyd": 151.879082,
        "hkd": 5.64698,
        "hnl": 17.554628,
        "hrk": 4.668508,
        "htg": 73.319513,
        "huf": 224.618708,
        "idr": 10337.955727,
        "ils": 2.297772,
        "imp": 0.532323,
        "inr": 54.303362,
        "iqd": 1059.968072,
        "irr": 30673.733562,
        "isk": 93.066901,
        "jep": 0.532323,
        "jmd": 112.121165,
        "jod": 0.51474,
        "jpy": 82.455714,
        "kes": 80.729113,
        "kgs": 61.563383,
        "khr": 2951.212668,
        "kmf": 305.942021,
        "kpw": 653.404758,
        "krw": 848.308345,
        "kwd": 0.218926,
        "kyd": 0.605007,
        "kzt": 310.588126,
        "lak": 7448.816716,
        "lbp": 1101.152997,
        "link": 0.024076,
        "lkr": 146.641114,
        "lrd": 109.995241,
        "lsl": 10.977435,
        "ltc": 0.003839,
        "ltl": 2.143706,
        "lvl": 0.439153,
        "lyd": 3.303278,
        "mad": 6.554741,
        "mdl": 12.703963,
        "mga": 2876.798497,
        "mkd": 38.290625,
        "mmk": 1303.074236,
        "mnt": 2069.786911,
        "mop": 5.815325,
        "mro": 259.183849,
        "mur": 31.254739,
        "mvr": 11.216618,
        "mwk": 591.694453,
        "mxn": 14.79671,
        "myr": 3.013026,
        "mzn": 46.34069,
        "nad": 10.976879,
        "ngn": 297.843971,
        "nio": 25.547208,
        "nok": 6.048897,
        "npr": 86.954665,
        "nzd": 1.009144,
        "omr": 0.279499,
        "pab": 0.725971,
        "pen": 2.887686,
        "pgk": 2.566412,
        "php": 36.526046,
        "pkr": 124.981739,
        "pln": 2.873058,
        "pyg": 5019.439563,
        "qar": 2.643371,
        "ron": 3.074486,
        "rsd": 73.553433,
        "rub": 51.118118,
        "rwf": 726.005529,
        "sar": 2.723259,
        "sbd": 5.831404,
        "scr": 10.202045,
        "sdg": 319.80572,
        "sek": 6.180369,
        "sgd": 0.975704,
        "shp": 1,
        "sll": 7822.70942,
        "sos": 423.987312,
        "srd": 15.578989,
        "std": 15026.848647,
        "svc": 6.352169,
        "syp": 912.568639,
        "szl": 10.977018,
        "thb": 24.095982,
        "theta": 0.11383,
        "tjs": 8.15949,
        "tmt": 2.54465,
        "tnd": 2.04189,
        "top": 1.623675,
        "trx": 7.63204,
        "try": 6.923508,
        "ttd": 4.909046,
        "twd": 20.136273,
        "tzs": 1669.812774,
        "uah": 19.119679,
        "ugx": 2580.709463,
        "usd": 0.726005,
        "usdt": 0.723815,
        "uyu": 31.618241,
        "uzs": 7760.999302,
        "vef": 155241923644.29303,
        "vnd": 16520.255808,
        "vuv": 81.527831,
        "wst": 1.870911,
        "xaf": 410.278234,
        "xag": 0.030164,
        "xau": 0.000403,
        "xcd": 1.962066,
        "xdr": 0.513945,
        "xlm": 2.111598,
        "xof": 410.555491,
        "xpf": 74.417995,
        "xrp": 0.683387,
        "yer": 181.6827,
        "zar": 10.979528,
        "zmk": 6534.920857,
        "zmw": 12.522239,
        "zwl": 233.773484
    }
}