{
    "fjd": {
        "aed": 1.833937,
        "afn": 39.117872,
        "all": 50.465137,
        "amd": 263.110068,
        "ang": 0.895888,
        "aoa": 324.44916,
        "ars": 44.815483,
        "aud": 0.634803,
        "awg": 0.898869,
        "azn": 0.84879,
        "bam": 0.798211,
        "bbd": 1.007751,
        "bch": 0.000999,
        "bdt": 42.322271,
        "bgn": 0.80183,
        "bhd": 0.188216,
        "bif": 970.555958,
        "bmd": 0.499289,
        "bnd": 0.658005,
        "bob": 3.446344,
        "brl": 2.761582,
        "bsd": 0.499121,
        "btc": 0.000011,
        "btn": 36.106713,
        "bwp": 5.428095,
        "byr": 1.300838,
        "bzd": 1.006037,
        "cad": 0.629735,
        "cdf": 991.0877,
        "chf": 0.452248,
        "clf": 0.012215,
        "clp": 357.490576,
        "cnh": 3.245178,
        "cny": 3.222857,
        "cop": 1802.796016,
        "crc": 305.198542,
        "cup": 11.97862,
        "cve": 45.002696,
        "czk": 10.776993,
        "djf": 88.733555,
        "dkk": 3.053449,
        "dop": 28.893527,
        "dzd": 66.278803,
        "egp": 7.840857,
        "etb": 20.132262,
        "eth": 0.000337,
        "eur": 0.410607,
        "fjd": 1,
        "gbp": 0.356442,
        "gel": 1.660134,
        "ghs": 2.872516,
        "gmd": 25.588536,
        "gnf": 5065.696383,
        "gqe": 267.706219,
        "gtq": 3.844376,
        "gyd": 104.382854,
        "hkd": 3.871558,
        "hnl": 12.02788,
        "hrk": 3.113613,
        "htg": 37.699768,
        "huf": 148.480915,
        "idr": 7152.307961,
        "ils": 1.637367,
        "inr": 36.523654,
        "iqd": 728.198817,
        "irr": 21022.542876,
        "isk": 62.935317,
        "jmd": 75.555034,
        "jod": 0.353996,
        "jpy": 53.097836,
        "kes": 54.801907,
        "kgs": 42.279552,
        "khr": 2041.638665,
        "kmf": 202.236813,
        "kpw": 1.821255,
        "krw": 559.163192,
        "kwd": 0.151085,
        "kyd": 0.415948,
        "kzt": 207.233193,
        "lak": 4663.699229,
        "lbp": 754.640138,
        "lkr": 97.077515,
        "lrd": 86.589111,
        "lsl": 7.249669,
        "ltc": 0.002783,
        "lyd": 2.220906,
        "mad": 4.435069,
        "mdl": 8.704606,
        "mga": 1874.690067,
        "mkd": 25.256694,
        "mmk": 703.749657,
        "mnt": 1407.993609,
        "mop": 3.986187,
        "mru": 17.949422,
        "mur": 19.846564,
        "mvr": 7.689043,
        "mwk": 389.965299,
        "mxn": 10.446159,
        "myr": 2.016876,
        "mzm": 37.399206,
        "mzn": 37.027236,
        "nad": 7.254662,
        "ngn": 190.268867,
        "nio": 17.419043,
        "nok": 4.246027,
        "npr": 57.770777,
        "nzd": 0.677747,
        "omr": 0.192221,
        "pab": 0.499121,
        "pen": 1.819568,
        "pgk": 1.760814,
        "php": 24.503582,
        "pkr": 79.022044,
        "pln": 1.855955,
        "pyg": 3297.62788,
        "qar": 1.817909,
        "ron": 2.00005,
        "rsd": 47.980018,
        "rub": 37.314177,
        "rwf": 495.758344,
        "sar": 1.872644,
        "sbd": 3.984907,
        "scr": 10.655815,
        "sdg": 187.482837,
        "sek": 4.143381,
        "sgd": 0.662988,
        "shp": 0.352697,
        "sll": 5090.745687,
        "sos": 292.583069,
        "srd": 7.06693,
        "svc": 4.367208,
        "syp": 627.106373,
        "szl": 7.377078,
        "thb": 15.110218,
        "tjs": 5.68761,
        "tmt": 1.752503,
        "tnd": 1.351824,
        "top": 1.136456,
        "try": 3.667771,
        "ttd": 3.392188,
        "twd": 13.865242,
        "tzs": 1157.350276,
        "uah": 13.92254,
        "ugx": 1829.240333,
        "usd": 0.499289,
        "uyu": 5.842301,
        "uzs": 1432.069461,
        "vef": 933824.300372,
        "vnd": 3130.493191,
        "vuv": 52.200614,
        "xaf": 266.555159,
        "xcd": 1.349352,
        "xof": 72.885888,
        "xpf": 49.229847,
        "yer": 34.037147,
        "zar": 7.506503,
        "zmw": 2.956164
    }
}