{
    "myr": {
        "aed": 0.909408,
        "afn": 19.202946,
        "all": 25.277024,
        "amd": 129.853924,
        "ang": 0.445147,
        "aoa": 161.539985,
        "ars": 22.085167,
        "aud": 0.314595,
        "awg": 0.445655,
        "azn": 0.420896,
        "bam": 0.399592,
        "bbd": 0.500719,
        "bch": 0.000364,
        "bdt": 20.996469,
        "bgn": 0.399586,
        "bhd": 0.093369,
        "bif": 482.069819,
        "bmd": 0.247586,
        "bnd": 0.328344,
        "bob": 1.714883,
        "brl": 1.332724,
        "bsd": 0.24799,
        "btc": 0.000004,
        "btn": 17.983451,
        "bwp": 2.686861,
        "byr": 0.642305,
        "bzd": 0.499881,
        "cad": 0.312342,
        "cdf": 489.601386,
        "chf": 0.221898,
        "clf": 0.006003,
        "clp": 175.451845,
        "cnh": 1.599901,
        "cny": 1.606041,
        "cop": 879.711067,
        "crc": 151.748032,
        "cup": 5.951872,
        "cve": 22.528066,
        "czk": 5.289861,
        "djf": 44.148997,
        "dkk": 1.519336,
        "dop": 14.361451,
        "dzd": 32.831146,
        "egp": 3.872461,
        "etb": 9.98588,
        "eth": 0.000129,
        "eur": 0.204308,
        "fjd": 0.501597,
        "gbp": 0.176639,
        "gel": 0.81951,
        "ghs": 1.432161,
        "gmd": 12.738302,
        "gnf": 2515.91483,
        "gqe": 134.017529,
        "gtq": 1.914513,
        "gyd": 51.88413,
        "hkd": 1.919584,
        "hnl": 5.976224,
        "hrk": 1.546794,
        "htg": 18.085789,
        "huf": 73.234712,
        "idr": 3482.745729,
        "ils": 0.809854,
        "inr": 17.967442,
        "iqd": 361.823966,
        "irr": 10424.610052,
        "isk": 31.790047,
        "jmd": 37.383932,
        "jod": 0.175365,
        "jpy": 26.12565,
        "kes": 27.205571,
        "kgs": 20.954444,
        "khr": 1008.834117,
        "kmf": 100.618965,
        "kpw": 0.903689,
        "krw": 273.58257,
        "kwd": 0.07492,
        "kyd": 0.206678,
        "kzt": 103.523075,
        "lak": 2317.020797,
        "lbp": 375.00817,
        "lkr": 48.482966,
        "lrd": 42.832384,
        "lsl": 3.637039,
        "ltc": 0.00109,
        "lyd": 1.104103,
        "mad": 2.207797,
        "mdl": 4.360983,
        "mga": 934.827433,
        "mkd": 12.588462,
        "mmk": 349.672444,
        "mnt": 698.192622,
        "mop": 1.980463,
        "mru": 8.903194,
        "mur": 9.841535,
        "mvr": 3.812825,
        "mwk": 193.104754,
        "mxn": 5.057494,
        "myr": 1,
        "mzm": 18.591235,
        "mzn": 18.405546,
        "nad": 3.637039,
        "ngn": 94.33028,
        "nio": 8.654912,
        "nok": 2.095519,
        "npr": 28.773583,
        "nzd": 0.338857,
        "omr": 0.095326,
        "pab": 0.24801,
        "pen": 0.905679,
        "pgk": 0.881918,
        "php": 12.006185,
        "pkr": 39.455954,
        "pln": 0.916341,
        "pyg": 1648.993563,
        "qar": 0.901461,
        "ron": 0.996286,
        "rsd": 24.018497,
        "rub": 18.330032,
        "rwf": 246.287645,
        "sar": 0.928448,
        "sbd": 1.982401,
        "scr": 5.323459,
        "sdg": 13.685318,
        "sek": 2.049591,
        "sgd": 0.3282,
        "shp": 0.176603,
        "sll": 2529.091359,
        "sos": 145.085417,
        "srd": 3.504333,
        "svc": 2.170164,
        "syp": 310.968061,
        "szl": 3.638324,
        "thb": 7.423867,
        "tjs": 2.825893,
        "tmt": 0.866551,
        "tnd": 0.670215,
        "top": 0.570092,
        "try": 1.724115,
        "ttd": 1.6825,
        "twd": 6.914806,
        "tzs": 575.09953,
        "uah": 6.906482,
        "ugx": 909.642238,
        "usd": 0.247586,
        "uyu": 2.891055,
        "uzs": 711.083735,
        "vef": 434615.498886,
        "vnd": 1554.214256,
        "vuv": 25.748948,
        "xaf": 133.448873,
        "xcd": 0.669114,
        "xof": 36.486219,
        "xpf": 24.424362,
        "yer": 16.876577,
        "zar": 3.627878,
        "zmw": 1.462743
    }
}