{
    "btn": {
        "aed": 0.049648,
        "afn": 1.042775,
        "all": 1.361082,
        "amd": 7.050864,
        "ang": 0.024245,
        "aoa": 8.845613,
        "ars": 1.122936,
        "aud": 0.017841,
        "awg": 0.024329,
        "azn": 0.022978,
        "bam": 0.021721,
        "bbd": 0.027272,
        "bch": 0.000043,
        "bdt": 1.145306,
        "bgn": 0.021599,
        "bhd": 0.005097,
        "bif": 26.316053,
        "bmd": 0.013516,
        "bnd": 0.018071,
        "bob": 0.09313,
        "brl": 0.069242,
        "bsd": 0.013507,
        "btc": 0.000001,
        "btn": 1,
        "bwp": 0.147133,
        "byr": 0.03402,
        "bzd": 0.027225,
        "cad": 0.017373,
        "cdf": 26.626925,
        "chf": 0.01197,
        "clf": 0.000337,
        "clp": 9.807359,
        "cnh": 0.088309,
        "cny": 0.088527,
        "cop": 46.374102,
        "crc": 8.189304,
        "cup": 0.013516,
        "cve": 1.221527,
        "czk": 0.289199,
        "djf": 2.4021,
        "dkk": 0.082171,
        "dop": 0.785967,
        "dzd": 1.786302,
        "egp": 0.211603,
        "etb": 0.524564,
        "eth": 0.000022,
        "eur": 0.011046,
        "fjd": 0.027636,
        "gbp": 0.01005,
        "gel": 0.044266,
        "ghs": 0.079408,
        "gmd": 0.699464,
        "gnf": 134.553829,
        "gqe": 7.28457,
        "gtq": 0.105352,
        "gyd": 2.82327,
        "hkd": 0.10479,
        "hnl": 0.32743,
        "hrk": 0.08324,
        "htg": 0.943756,
        "huf": 3.981469,
        "idr": 191.896332,
        "ils": 0.043966,
        "inr": 1.002429,
        "iqd": 16.097801,
        "irr": 569.099845,
        "isk": 1.727236,
        "jmd": 1.934777,
        "jod": 0.009583,
        "jpy": 1.396413,
        "kes": 1.50165,
        "kgs": 1.089406,
        "khr": 54.673052,
        "kmf": 5.440949,
        "kpw": 0.048722,
        "krw": 14.939462,
        "kwd": 0.004112,
        "kyd": 0.011256,
        "kzt": 5.690158,
        "lak": 125.565552,
        "lbp": 20.49073,
        "lkr": 2.538598,
        "lrd": 2.187598,
        "lsl": 0.196526,
        "ltc": 0.000128,
        "lyd": 0.018112,
        "mad": 0.121071,
        "mdl": 0.232683,
        "mga": 50.55061,
        "mkd": 0.68026,
        "mmk": 17.997761,
        "mnt": 38.021087,
        "mop": 0.107858,
        "mru": 0.489557,
        "mur": 0.531878,
        "mvr": 0.20815,
        "mwk": 10.407478,
        "mxn": 0.270184,
        "myr": 0.054612,
        "mzm": 1.011012,
        "mzn": 1.000875,
        "nad": 0.196593,
        "ngn": 5.136158,
        "nio": 0.471851,
        "nok": 0.11677,
        "npr": 1.599998,
        "nzd": 0.019048,
        "omr": 0.005205,
        "pab": 0.013506,
        "pen": 0.048723,
        "pgk": 0.047442,
        "php": 0.651819,
        "pkr": 2.167324,
        "pln": 0.049622,
        "pyg": 93.784735,
        "qar": 0.049213,
        "ron": 0.053722,
        "rsd": 1.297961,
        "rub": 1.008124,
        "rwf": 13.279672,
        "sar": 0.050701,
        "sbd": 0.108592,
        "scr": 0.28665,
        "sdg": 0.746095,
        "sek": 0.111483,
        "sgd": 0.018012,
        "shp": 0.01014,
        "sll": 136.61505,
        "sos": 7.893464,
        "srd": 0.191308,
        "svc": 0.118183,
        "syp": 16.976354,
        "szl": 0.196526,
        "thb": 0.407061,
        "tjs": 0.152757,
        "tmt": 0.047307,
        "tnd": 0.036359,
        "top": 0.0308,
        "try": 0.103418,
        "ttd": 0.091898,
        "twd": 0.377778,
        "tzs": 31.344081,
        "uah": 0.380056,
        "ugx": 49.298847,
        "usd": 0.013516,
        "uyu": 0.155747,
        "uzs": 38.533626,
        "vef": 14435.632179,
        "vnd": 85.111035,
        "vuv": 1.447991,
        "xaf": 7.202651,
        "xcd": 0.036528,
        "xof": 1.985188,
        "xpf": 1.323237,
        "yer": 0.921208,
        "zar": 0.197433,
        "zmw": 0.077751
    }
}